wyn_voice/__init__.py
wyn_voice/chat.py
wyn_voice-0.2.3.dist-info/METADATA
wyn_voice-0.2.3.dist-info/WHEEL
wyn_voice-0.2.3.dist-info/RECORD
